alexwlchan_chives-22.dist-info/licenses/LICENSE
chives/__init__.py
chives/dates.py
chives/media.py
chives/py.typed
chives/static_site_tests.py
chives/urls.py
alexwlchan_chives-22.dist-info/METADATA
alexwlchan_chives-22.dist-info/WHEEL
alexwlchan_chives-22.dist-info/top_level.txt
alexwlchan_chives-22.dist-info/RECORD
