Metadata-Version: 2.4
Name: alexwlchan-chives
Version: 22
Summary: Utility functions for working with my local media archives
Author-email: Alex Chan <alex@alexwlchan.net>
Maintainer-email: Alex Chan <alex@alexwlchan.net>
License-Expression: MIT
Project-URL: Homepage, https://github.com/alexwlchan/chives
Project-URL: Changelog, https://github.com/alexwlchan/chives/blob/main/CHANGELOG.md
Classifier: Development Status :: 4 - Beta
Classifier: Programming Language :: Python :: 3.13
Requires-Python: >=3.13
License-File: LICENSE
Provides-Extra: media
Requires-Dist: Pillow; extra == "media"
Provides-Extra: static-site-tests
Requires-Dist: pytest; extra == "static-site-tests"
Requires-Dist: rapidfuzz; extra == "static-site-tests"
Provides-Extra: urls
Requires-Dist: httpx; extra == "urls"
Requires-Dist: hyperlink; extra == "urls"
Dynamic: license-file
